README.md
setup.py
py_reuse.egg-info/PKG-INFO
py_reuse.egg-info/SOURCES.txt
py_reuse.egg-info/dependency_links.txt
py_reuse.egg-info/top_level.txt
reuse/__init__.py
test/test.py