Metadata-Version: 1.0
Name: py-reuse
Version: 0.0.3
Summary: Collection of useful python functions
Home-page: https://github.com/vra/reuse
Author: Yunfeng Wang
Author-email: wyf.brz@gmail.com
License: UNKNOWN
Platform: UNKNOWN
